openg2p_g2p_bridge_example_bank_models/__init__.py
openg2p_g2p_bridge_example_bank_models/models/__init__.py
openg2p_g2p_bridge_example_bank_models/models/account.py
openg2p_g2p_bridge_example_bank_models/models/account_statement.py
openg2p_g2p_bridge_example_bank_models/models/payment_request.py
openg2p_g2p_bridge_example_bank_models/schemas/__init__.py
openg2p_g2p_bridge_example_bank_models/schemas/account.py
openg2p_g2p_bridge_example_bank_models/schemas/account_statement.py
openg2p_g2p_bridge_example_bank_models/schemas/payment_request.py
openg2p_g2p_bridge_example_bank_models-1.0.2.dist-info/METADATA
openg2p_g2p_bridge_example_bank_models-1.0.2.dist-info/WHEEL
openg2p_g2p_bridge_example_bank_models-1.0.2.dist-info/licenses/LICENSE
openg2p_g2p_bridge_example_bank_models-1.0.2.dist-info/RECORD
