Metadata-Version: 2.3
Name: openg2p-g2p-bridge-example-bank-models
Version: 1.0.2
Summary: OpenG2P G2P Bridge Example Bank Models
Project-URL: Homepage, https://openg2p.org
Project-URL: Documentation, https://docs.openg2p.org/
Project-URL: Repository, https://github.com/OpenG2P/openg2p-g2p-bridge-example-bank
Project-URL: Source, https://github.com/OpenG2P/openg2p-g2p-bridge-example-bank
Author-email: OpenG2P <info@openg2p.org>
Classifier: License :: OSI Approved :: Mozilla Public License 2.0 (MPL 2.0)
Classifier: Operating System :: OS Independent
Classifier: Programming Language :: Python :: 3
Requires-Python: >=3.7
Requires-Dist: openg2p-fastapi-auth
Requires-Dist: openg2p-fastapi-common
